ara_imgui/__init__.py
ara_imgui/app.py
ara_imgui/window.py
ara_imgui-1.3.0.dist-info/METADATA
ara_imgui-1.3.0.dist-info/WHEEL
ara_imgui-1.3.0.dist-info/top_level.txt
ara_imgui-1.3.0.dist-info/RECORD
