Metadata-Version: 2.4
Name: Ara_imgui
Version: 1.3.0
Summary: A simplified wrapper for Dear ImGui and GLFW
Author-email: HanamileH <hanamileh@gmail.com>
License-Expression: MIT
Project-URL: Homepage, https://github.com/hanamileh-DEV/Ara_imgui
Requires-Python: >=3.7
Requires-Dist: glfw>=2.8.0
Requires-Dist: imgui==2.0.0
Requires-Dist: pyopengl>=3.1.9
